[
  {
    "anonymous": false,
    "inputs": [
      {
        "indexed": true,
        "internalType": "contract BadgerOrganization",
        "name": "organization",
        "type": "address"
      },
      {
        "indexed": true,
        "internalType": "address",
        "name": "owner",
        "type": "address"
      },
      {
        "indexed": true,
        "internalType": "uint256",
        "name": "organizationId",
        "type": "uint256"
      }
    ],
    "name": "OrganizationCreated",
    "type": "event"
  },
  {
    "inputs": [
      {
        "components": [
          {
            "internalType": "address",
            "name": "deployer",
            "type": "address"
          },
          {
            "internalType": "string",
            "name": "uri",
            "type": "string"
          },
          {
            "internalType": "string",
            "name": "organizationURI",
            "type": "string"
          },
          {
            "internalType": "string",
            "name": "name",
            "type": "string"
          },
          {
            "internalType": "string",
            "name": "symbol",
            "type": "string"
          }
        ],
        "internalType": "struct IBadger.Organization",
        "name": "_organization",
        "type": "tuple"
      }
    ],
    "name": "createOrganization",
    "outputs": [
      {
        "internalType": "contract BadgerOrganization",
        "name": "badgerOrganization",
        "type": "address"
      },
      {
        "internalType": "uint256",
        "name": "organizationId",
        "type": "uint256"
      }
    ],
    "stateMutability": "nonpayable",
    "type": "function"
  },
  {
    "inputs": [
      {
        "internalType": "uint256",
        "name": "_organizationId",
        "type": "uint256"
      }
    ],
    "name": "getOrganization",
    "outputs": [
      {
        "internalType": "contract BadgerOrganization",
        "name": "",
        "type": "address"
      }
    ],
    "stateMutability": "view",
    "type": "function"
  },
  {
    "inputs": [],
    "name": "getOrganizationURI",
    "outputs": [
      {
        "internalType": "string",
        "name": "",
        "type": "string"
      }
    ],
    "stateMutability": "view",
    "type": "function"
  }
]
